{
  "dummyData": [
    {
      "tasks": [

      ],
      "dependencies": [
      ],
      "resources": [
        {
          "id": 1,
          "text": "TAS; Tasarımcı-1",
          "resourceType": "Tasarım Ekibi"
        },
        {
          "id": 2,
          "text": "TAS; Tasarımcı-2",
          "resourceType": "Tasarım Ekibi"
        },
        {
          "id": 3,
          "text": "TAS; Tasarımcı-3",
          "resourceType": "Tasarım Ekibi"
        },
        {
          "id": 4,
          "text": "PRO; Proje Yöneticisi-1",
          "resourceType": "Proje Yöneticileri"
        },
        {
          "id": 5,
          "text": "PRO; Proje Yöneticisi-2",
          "resourceType": "Proje Yöneticileri"
        },
        {
          "id": 6,
          "text": "PRO; Proje Yöneticisi-3",
          "resourceType": "Proje Yöneticileri"
        },
        {
          "id": 7,
          "text": "TEK; Çalışan-1",
          "resourceType": "Teknik Servis Ekibi"
        },
        {
          "id": 8,
          "text": "TEK; Çalışan-2",
          "resourceType": "Teknik Servis Ekibi"
        },
        {
          "id": 9,
          "text": "TEK; Çalışan-3",
          "resourceType": "Teknik Servis Ekibi"
        },
        {
          "id": 10,
          "text": "Henüz Belirlenmedi",
          "resourceType": "Daha Sonra Güncellenecek"
        },
        {
          "id": 11,
          "text": "ÜRE; Iş Merkezi-1",
          "resourceType": "Üretım Kaynakları"
        },
        {
          "id": 12,
          "text": "ÜRE; Iş Merkezi-2",
          "resourceType": "Üretım Kaynakları"
        },
        {
          "id": 13,
          "text": "ÜRE; Iş Merkezi-3",
          "resourceType": "Üretım Kaynakları"
        },
        {
          "id": 14,
          "text": "DIŞ; Fason-1",
          "resourceType": "Dış Kaynaklar"
        },
        {
          "id": 15,
          "text": "DIŞ; Fason-2",
          "resourceType": "Dış Kaynaklar"
        },
        {
          "id": 16,
          "text": "DIŞ; Fason-3",
          "resourceType": "Dış Kaynaklar"
        },
        {
          "id": 18,
          "text": "SAT; Satış Elemanı-1",
          "resourceType": "Satış Pazarlama Ekibi"
        },
        {
          "id": 19,
          "text": "SAT; Satış Elemanı-2",
          "resourceType": "Satış Pazarlama Ekibi"
        },
        {
          "id": 20,
          "text": "SAT; Satış Elemanı-3",
          "resourceType": "Satış Pazarlama Ekibi"
        },
        {
          "id": 21,
          "text": "TES; Tester-1",
          "resourceType": "Test Ekibi"
        },
        {
          "id": 22,
          "text": "TES; Tester-2",
          "resourceType": "Test Ekibi"
        },
        {
          "id": 23,
          "text": "TES; Tester-3",
          "resourceType": "Test Ekibi"
        },
        {
          "id": 24,
          "text": "Erp'de Yok",
          "resourceType": "Daha Sonra Güncellenecek"
        }

      ],
      "resourceAssignments": [
        {
          "id": 0,
          "taskId": 3,
          "resourceId": 1
        }
      ],
      "taskStatusListOrder": [
        {
          "statusId": 1,
          "statusName": "Tasarımdayken Başka Projeye Geçildi",
          "statusdisplayColor": "Açık Mavi",
          "statusGroup": "Tasarım Iş Listesi"
        },
        {
          "statusId": 2,
          "statusName": "Tasarım Bitti",
          "statusdisplayColor": "Açık Yeşil",
          "statusGroup": "Tasarım Iş Listesi"
        },
        {
          "statusId": 3,
          "statusName": "Tasarım İptal",
          "statusdisplayColor": "Açık Sarı",
          "statusGroup": "Tasarım Iş Listesi"
        },
        {
          "statusId": 4,
          "statusName": "Tasarım Beklemede",
          "statusdisplayColor": "Turuncu",
          "statusGroup": "Tasarım Iş Listesi"
        },
        {
          "statusId": 5,
          "statusName": "Tasarım Aşamasında",
          "statusdisplayColor": "Açık Gri",
          "statusGroup": "Tasarım Iş Listesi"
        },
        {
          "statusId": 6,
          "statusName": "Sipariş veya Revizyon Formu Revizyona Uğramıştır",
          "statusdisplayColor": "Siyah",
          "statusGroup": "Tasarım Iş Listesi"
        },
        {
          "statusId": 7,
          "statusName": "Müşteriden Bilgi Bekleniyor",
          "statusdisplayColor": "Açık Mor",
          "statusGroup": "Tasarım Iş Listesi"
        },
        {
          "statusId": 8,
          "statusName": "Müşteri Onayı Bekleniyor",
          "statusdisplayColor": "Koyu Pembe",
          "statusGroup": "Tasarım Iş Listesi"
        },
        {
          "statusId": 9,
          "statusName": "Testi Yapılan(Hazır) Proje",
          "statusdisplayColor": "Koyu Gri",
          "statusGroup": "Robot Süreçleri"
        },
        {
          "statusId": 10,
          "statusName": "Testte Olan Proje",
          "statusdisplayColor": "Koyu Mavi",
          "statusGroup": "Robot Süreçleri"
        },
        {
          "statusId": 11,
          "statusName": "Yükleme Yapılan Proje",
          "statusdisplayColor": "Kırmızı",
          "statusGroup": "Robot Süreçleri"
        },
        {
          "statusId": 12,
          "statusName": "Tasarımda Olan Proje",
          "statusdisplayColor": "Koyu Mor",
          "statusGroup": "Robot Süreçleri"
        },
        {
          "statusId": 13,
          "statusName": "İmalatta Olan Proje",
          "statusdisplayColor": "Koyu Gri",
          "statusGroup": "Robot Süreçleri"
        },
        {
          "statusId": 14,
          "statusName": "Kamerada Olan Proje",
          "statusdisplayColor": "Koyu Sarı",
          "statusGroup": "Robot Süreçleri"
        },
        {
          "statusId": 15,
          "statusName": "Operasyon Başladı",
          "statusdisplayColor": "Çok Açık Yeşil",
          "statusGroup": "Operasyon Süreçleri"
        },
        {
          "statusId": 16,
          "statusName": "Operasyon Tamamlandı",
          "statusdisplayColor": "Koyu Yeşil",
          "statusGroup": "Operasyon Süreçleri"
        },
        {
          "statusId": 17,
          "statusName": "Operasyon Durdu",
          "statusdisplayColor": "Sarı",
          "statusGroup": "Operasyon Süreçleri"
        },
        {
          "statusId": 18,
          "statusName": "Operasyon Iptal",
          "statusdisplayColor": "Kırmızı",
          "statusGroup": "Operasyon Süreçleri"
        },
        {
          "statusId": 19,
          "statusName": "Operasyon Bekliyor",
          "statusdisplayColor": "Beyaz",
          "statusGroup": "Operasyon Süreçleri"
        },
        {
          "statusId": 20,
          "statusName": "Henüz Belirlenmedi",
          "statusdisplayColor": "Beyaz",
          "statusGroup": "ERP"
        },
        {
          "statusId": 21,
          "statusName": "Ön Hazırlığı Yapılan Proje",
          "statusdisplayColor": "Pembe",
          "statusGroup": "Robot Süreçleri"
        }
      ],
      "taskOperationList": [
        {
          "id": 1,
          "name": "Sipariş Süreci",
          "displayColor": "Çok Açık Mavi",
          "variousInfoRelations": [
            {}
          ],
          "routeLevelNumber": 1,
          "routeLevelName": "Proje Süreçleri",
          "preRouteId": 0
        },
        {
          "id": 2,
          "name": "Siparişin Alınması",
          "displayColor": "Çok Açık Mavi",
          "variousInfoRelations": [
            {}
          ],
          "routeLevelNumber": 2,
          "routeLevelName": "Sipariş Süreci",
          "preRouteId": 1
        },
        {
          "id": 3,
          "name": "Sipariş Bilgi Toplama",
          "displayColor": "Çok Açık Mavi",
          "variousInfoRelations": [
            {}
          ],
          "routeLevelNumber": 2,
          "routeLevelName": "Sipariş Süreci",
          "preRouteId": 1
        },
        {
          "id": 4,
          "name": "Tasarım Süreci",
          "displayColor": "Bej",
          "variousInfoRelations": [
            {}
          ],
          "routeLevelNumber": 1,
          "routeLevelName": "Proje Süreçleri",
          "preRouteId": 0
        },
        {
          "id": 5,
          "name": "Tasarım Işlemleri",
          "displayColor": "Bej",
          "variousInfoRelations": [
            {}
          ],
          "routeLevelNumber": 2,
          "routeLevelName": "Tasarım Süreci",
          "preRouteId": 4
        },
        {
          "id": 6,
          "name": "Imalat Resminin Hazırlanması",
          "displayColor": "Bej",
          "variousInfoRelations": [
            {}
          ],
          "routeLevelNumber": 1,
          "routeLevelName": "Tasarım Süreci",
          "preRouteId": 0
        },
        {
          "id": 7,
          "name": "Şase Üretim Süreci",
          "displayColor": "Açık Mavi",
          "variousInfoRelations": [
            {}
          ],
          "routeLevelNumber": 1,
          "routeLevelName": "Proje Süreçleri",
          "preRouteId": 0
        },
        {
          "id": 8,
          "name": "Şase; Dış Imalat",
          "displayColor": "Açık Mavi",
          "variousInfoRelations": [
            {}
          ],
          "routeLevelNumber": 2,
          "routeLevelName": "Şase Üretim Süreci",
          "preRouteId": 7
        },
        {
          "id": 9,
          "name": "Şase; Lazer Kesim",
          "displayColor": "Açık Mavi",
          "variousInfoRelations": [
            {}
          ],
          "routeLevelNumber": 2,
          "routeLevelName": "Şase Üretim Süreci",
          "preRouteId": 7
        },
        {
          "id": 10,
          "name": "Şase; Kaynak",
          "displayColor": "Açık Mavi",
          "variousInfoRelations": [
            {}
          ],
          "routeLevelNumber": 2,
          "routeLevelName": "Şase Üretim Süreci",
          "preRouteId": 7
        },
        {
          "id": 11,
          "name": "Şase; Teslim",
          "displayColor": "Açık Mavi",
          "variousInfoRelations": [
            {}
          ],
          "routeLevelNumber": 2,
          "routeLevelName": "Şase Üretim Süreci",
          "preRouteId": 7
        },
        {
          "id": 12,
          "name": "Dizme Üretim Süreci",
          "displayColor": "Açık Turuncu",
          "variousInfoRelations": [
            {}
          ],
          "routeLevelNumber": 1,
          "routeLevelName": "Proje Süreçleri",
          "preRouteId": 0
        },
        {
          "id": 13,
          "name": "Dizme; Iç Imalat",
          "displayColor": "Açık Turuncu",
          "variousInfoRelations": [
            {}
          ],
          "routeLevelNumber": 2,
          "routeLevelName": "Dizme Üretim Süreci",
          "preRouteId": 12
        },
        {
          "id": 14,
          "name": "Dizme; Dış Imalat",
          "displayColor": "Açık Turuncu",
          "variousInfoRelations": [
            {}
          ],
          "routeLevelNumber": 2,
          "routeLevelName": "Dizme Üretim Süreci",
          "preRouteId": 12
        },
        {
          "id": 15,
          "name": "Dizme; Satın Alma / Depo",
          "displayColor": "Açık Turuncu",
          "variousInfoRelations": [
            {}
          ],
          "routeLevelNumber": 2,
          "routeLevelName": "Dizme Üretim Süreci",
          "preRouteId": 12
        },
        {
          "id": 16,
          "name": "Dizme; Montaj",
          "displayColor": "Açık Turuncu",
          "variousInfoRelations": [
            {}
          ],
          "routeLevelNumber": 2,
          "routeLevelName": "Dizme Üretim Süreci",
          "preRouteId": 12
        },
        {
          "id": 17,
          "name": "Dizme; Tesisat",
          "displayColor": "Açık Turuncu",
          "variousInfoRelations": [
            {}
          ],
          "routeLevelNumber": 2,
          "routeLevelName": "Dizme Üretim Süreci",
          "preRouteId": 12
        },
        {
          "id": 18,
          "name": "Ana Aks Kol Üretim Süreci",
          "displayColor": "Açık Mor",
          "variousInfoRelations": [
            {}
          ],
          "routeLevelNumber": 1,
          "routeLevelName": "Proje Süreçleri",
          "preRouteId": 0
        },
        {
          "id": 19,
          "name": "Ana Aks Kol; Iç Imalat",
          "displayColor": "Açık Mor",
          "variousInfoRelations": [
            {}
          ],
          "routeLevelNumber": 2,
          "routeLevelName": "Ana Aks Kol Üretim Süreci",
          "preRouteId": 18
        },
        {
          "id": 20,
          "name": "Ana Aks Kol; Dış Imalat ",
          "displayColor": "Açık Mor",
          "variousInfoRelations": [
            {}
          ],
          "routeLevelNumber": 2,
          "routeLevelName": "Ana Aks Kol Üretim Süreci",
          "preRouteId": 18
        },
        {
          "id": 21,
          "name": "Ana Aks Kol; Satın Alma / Depo ",
          "displayColor": "Açık Mor",
          "variousInfoRelations": [
            {}
          ],
          "routeLevelNumber": 2,
          "routeLevelName": "Ana Aks Kol Üretim Süreci",
          "preRouteId": 18
        },
        {
          "id": 22,
          "name": "Ana Aks Kol; Montaj ",
          "displayColor": "Açık Mor",
          "variousInfoRelations": [
            {}
          ],
          "routeLevelNumber": 2,
          "routeLevelName": "Ana Aks Kol Üretim Süreci",
          "preRouteId": 18
        },
        {
          "id": 23,
          "name": "Ana Aks Kol; Tesisat ",
          "displayColor": "Açık Mor",
          "variousInfoRelations": [
            {}
          ],
          "routeLevelNumber": 2,
          "routeLevelName": "Ana Aks Kol Üretim Süreci",
          "preRouteId": 18
        },
        {
          "id": 24,
          "name": "Seperatör Üretim Süreci",
          "displayColor": "Açık Yeşil",
          "variousInfoRelations": [
            {}
          ],
          "routeLevelNumber": 1,
          "routeLevelName": "Proje Süreçleri",
          "preRouteId": 0
        },
        {
          "id": 25,
          "name": "Seperatör; Iç Imalat",
          "displayColor": "Açık Yeşil",
          "variousInfoRelations": [
            {}
          ],
          "routeLevelNumber": 2,
          "routeLevelName": "Seperatör Üretim Süreci",
          "preRouteId": 24
        },
        {
          "id": 26,
          "name": "Seperatör; Dış Imalat",
          "displayColor": "Açık Yeşil",
          "variousInfoRelations": [
            {}
          ],
          "routeLevelNumber": 2,
          "routeLevelName": "Seperatör Üretim Süreci",
          "preRouteId": 24
        },
        {
          "id": 27,
          "name": "Seperatör; Satın Alma / Depo",
          "displayColor": "Açık Yeşil",
          "variousInfoRelations": [
            {}
          ],
          "routeLevelNumber": 2,
          "routeLevelName": "Seperatör Üretim Süreci",
          "preRouteId": 24
        },
        {
          "id": 28,
          "name": "Seperatör; Montaj",
          "displayColor": "Açık Yeşil",
          "variousInfoRelations": [
            {}
          ],
          "routeLevelNumber": 2,
          "routeLevelName": "Seperatör Üretim Süreci",
          "preRouteId": 24
        },
        {
          "id": 29,
          "name": "Seperatör; Tesisat",
          "displayColor": "Açık Yeşil",
          "variousInfoRelations": [
            {}
          ],
          "routeLevelNumber": 2,
          "routeLevelName": "Seperatör Üretim Süreci",
          "preRouteId": 24
        },
        {
          "id": 30,
          "name": "Test",
          "displayColor": "Gri",
          "variousInfoRelations": [
            {}
          ],
          "routeLevelNumber": 1,
          "routeLevelName": "Proje Süreçleri",
          "preRouteId": 0
        },
        {
          "id": 31,
          "name": "Test; Mekanik Ayar",
          "displayColor": "Gri",
          "variousInfoRelations": [
            {}
          ],
          "routeLevelNumber": 2,
          "routeLevelName": "Test",
          "preRouteId": 30
        },
        {
          "id": 32,
          "name": "Test; Elektrik Testi",
          "displayColor": "Gri",
          "variousInfoRelations": [
            {}
          ],
          "routeLevelNumber": 2,
          "routeLevelName": "Test",
          "preRouteId": 30
        },
        {
          "id": 33,
          "name": "Test; Yazılım Testi",
          "displayColor": "Gri",
          "variousInfoRelations": [
            {}
          ],
          "routeLevelNumber": 2,
          "routeLevelName": "Test",
          "preRouteId": 30
        },
        {
          "id": 34,
          "name": "Test; Proje Kontrol",
          "displayColor": "Gri",
          "variousInfoRelations": [
            {}
          ],
          "routeLevelNumber": 2,
          "routeLevelName": "Test",
          "preRouteId": 30
        },
        {
          "id": 35,
          "name": "Yükleme Formunun Hazırlanması",
          "displayColor": "Açık Kahverengi",
          "variousInfoRelations": [
            {}
          ],
          "routeLevelNumber": 1,
          "routeLevelName": "Proje Süreçleri",
          "preRouteId": 0
        },
        {
          "id": 36,
          "name": "Yüklemenin Gerçekleştirilmesi",
          "displayColor": "Koyu Kahverengi",
          "variousInfoRelations": [
            {}
          ],
          "routeLevelNumber": 1,
          "routeLevelName": "Proje Süreçleri",
          "preRouteId": 0
        },
        {
          "id": 37,
          "name": "Etiket Transfer Üretim Süreci",
          "displayColor": "Açık Yeşil",
          "variousInfoRelations": [
            {}
          ],
          "routeLevelNumber": 1,
          "routeLevelName": "Proje Süreçleri",
          "preRouteId": 0
        },
        {
          "id": 38,
          "name": "Etiket Transfer; Iç Imalat",
          "displayColor": "Açık Yeşil",
          "variousInfoRelations": [
            {}
          ],
          "routeLevelNumber": 2,
          "routeLevelName": "Etiket Transfer Üretim Süreci",
          "preRouteId": 37
        },
        {
          "id": 39,
          "name": "Etiket Transfer; Dış Imalat",
          "displayColOrderor": "Açık Yeşil",
          "variousInfoRelations": [
            {}
          ],
          "routeLevelNumber": 2,
          "routeLevelName": "Etiket Transfer Üretim Süreci",
          "preRouteId": 37
        },
        {
          "id": 40,
          "name": "Etiket Transfer; Satın Alma / Depo",
          "displayColor": "Açık Yeşil",
          "variousInfoRelations": [
            {}
          ],
          "routeLevelNumber": 2,
          "routeLevelName": "Etiket Transfer Üretim Süreci",
          "preRouteId": 37
        },
        {
          "id": 41,
          "name": "Etiket Transfer; Montaj",
          "displayColor": "Açık Yeşil",
          "variousInfoRelations": [
            {}
          ],
          "routeLevelNumber": 2,
          "routeLevelName": "Etiket Transfer Üretim Süreci",
          "preRouteId": 37
        },
        {
          "id": 42,
          "name": "Etiket Transfer; Tesisat",
          "displayColor": "Açık Yeşil",
          "variousInfoRelations": [
            {}
          ],
          "routeLevelNumber": 2,
          "routeLevelName": "Etiket Transfer Üretim Süreci",
          "preRouteId": 37
        },
        {
          "id": 43,
          "name": "Yeni Proje/Görev/Operasyon",
          "displayColor": "Beyaz",
          "variousInfoRelations": [
            {}
          ],
          "routeLevelNumber": 1,
          "routeLevelName": "ERP",
          "preRouteId": 0
        }
      ]
    }
  ]
}
